msprechecker/__init__.py
msprechecker/cli.py
msprechecker/checkers/__init__.py
msprechecker/checkers/ascend.py
msprechecker/checkers/base.py
msprechecker/checkers/env.py
msprechecker/checkers/hccl.py
msprechecker/checkers/network.py
msprechecker/checkers/pd.py
msprechecker/checkers/stress.py
msprechecker/checkers/sys.py
msprechecker/checkers/config/__init__.py
msprechecker/checkers/config/mies_config.py
msprechecker/checkers/config/mindie_env.py
msprechecker/checkers/config/model_config.py
msprechecker/checkers/config/user_config.py
msprechecker/cmate/__init__.py
msprechecker/cmate/_ast.py
msprechecker/cmate/_test.py
msprechecker/cmate/cmate.py
msprechecker/cmate/custom_fn.py
msprechecker/cmate/data_source.py
msprechecker/cmate/lexer.py
msprechecker/cmate/parser.py
msprechecker/cmate/util.py
msprechecker/cmate/visitor.py
msprechecker/collectors/__init__.py
msprechecker/collectors/ascend.py
msprechecker/collectors/base.py
msprechecker/collectors/config.py
msprechecker/collectors/env.py
msprechecker/collectors/hccl.py
msprechecker/collectors/network.py
msprechecker/collectors/sys.py
msprechecker/collectors/weight.py
msprechecker/collectors/hardware/__init__.py
msprechecker/collectors/hardware/base.py
msprechecker/collectors/hardware/cpu.py
msprechecker/collectors/hardware/matmul_shape.yaml
msprechecker/collectors/hardware/npu.py
msprechecker/commands/__init__.py
msprechecker/commands/_cmate.py
msprechecker/commands/banner.py
msprechecker/commands/base.py
msprechecker/commands/compare.py
msprechecker/commands/coordinator.py
msprechecker/commands/dump.py
msprechecker/commands/legacy.py
msprechecker/commands/precheck.py
msprechecker/comparators/__init__.py
msprechecker/presets/__init__.py
msprechecker/presets/default.yaml
msprechecker/presets/manager.py
msprechecker/presets/mindie.cmate
msprechecker/presets/vllm.cmate
msprechecker/presets/A2/arm/config_check_dsr1_pd.yaml
msprechecker/presets/A2/arm/config_check_pd.yaml
msprechecker-0.3.4.dist-info/METADATA
msprechecker-0.3.4.dist-info/WHEEL
msprechecker-0.3.4.dist-info/entry_points.txt
msprechecker-0.3.4.dist-info/top_level.txt
msprechecker-0.3.4.dist-info/RECORD
