Metadata-Version: 2.4
Name: msprechecker
Version: 0.3.4
Summary: MindStudio Prechecker
Author-email: AvadaKedavrua <anonymousdev@163.com>
License: Apache-2.0
Project-URL: source, https://gitcode.com/Ascend/msit/tree/master/msprechecker
Project-URL: documentation, https://gitcode.com/Ascend/msit/tree/master/msprechecker
Project-URL: tracker, https://gitcode.com/Ascend/msit/issues
Keywords: MindStudio,precheck
Classifier: Programming Language :: Python :: 3.7
Classifier: Programming Language :: Python :: 3.8
Classifier: Programming Language :: Python :: 3.9
Classifier: Programming Language :: Python :: 3.10
Classifier: Programming Language :: Python :: 3.11
Classifier: Operating System :: OS Independent
Requires-Python: >=3.7
Requires-Dist: pyyaml
Requires-Dist: psutil
Requires-Dist: importlib_metadata; python_version == "3.7"
Requires-Dist: msguard
Requires-Dist: ply
Requires-Dist: colorama
Provides-Extra: test
Requires-Dist: pytest; extra == "test"
Requires-Dist: pytest-mocker; extra == "test"
